deptry-0.24.0.dist-info/METADATA
deptry-0.24.0.dist-info/WHEEL
deptry-0.24.0.dist-info/entry_points.txt
deptry-0.24.0.dist-info/licenses/LICENSE
deptry/__init__.py
deptry/__main__.py
deptry/cli.py
deptry/config.py
deptry/core.py
deptry/dependency.py
deptry/dependency_getter/__init__.py
deptry/dependency_getter/base.py
deptry/dependency_getter/builder.py
deptry/dependency_getter/pep621/__init__.py
deptry/dependency_getter/pep621/base.py
deptry/dependency_getter/pep621/pdm.py
deptry/dependency_getter/pep621/poetry.py
deptry/dependency_getter/pep621/uv.py
deptry/dependency_getter/requirements_files.py
deptry/exceptions.py
deptry/imports/__init__.py
deptry/imports/extract.py
deptry/imports/location.py
deptry/module.py
deptry/python_file_finder.py
deptry/reporters/__init__.py
deptry/reporters/base.py
deptry/reporters/github.py
deptry/reporters/json.py
deptry/reporters/text.py
deptry/rust.pyi
deptry/rust.pypy311-pp73-darwin.so
deptry/utils.py
deptry/violations/__init__.py
deptry/violations/base.py
deptry/violations/dep001_missing/__init__.py
deptry/violations/dep001_missing/finder.py
deptry/violations/dep001_missing/violation.py
deptry/violations/dep002_unused/__init__.py
deptry/violations/dep002_unused/finder.py
deptry/violations/dep002_unused/violation.py
deptry/violations/dep003_transitive/__init__.py
deptry/violations/dep003_transitive/finder.py
deptry/violations/dep003_transitive/violation.py
deptry/violations/dep004_misplaced_dev/__init__.py
deptry/violations/dep004_misplaced_dev/finder.py
deptry/violations/dep004_misplaced_dev/violation.py
deptry/violations/dep005_standard_library/__init__.py
deptry/violations/dep005_standard_library/finder.py
deptry/violations/dep005_standard_library/violation.py
deptry/violations/finder.py
deptry-0.24.0.dist-info/RECORD
